{"type": "struct", "fields": [{"name": "RECORD_IDENTIFIER", "type": "integer", "nullable": true, "metadata": {}}, {"name": "CUSTODIAN_NAME", "type": "string", "nullable": true, "metadata": {}}, {"name": "LOCAL_CUSTODIAN_NAME", "type": "string", "nullable": true, "metadata": {}}, {"name": "PROCESS_DATE", "type": "date", "nullable": true, "metadata": {}}, {"name": "VOLUME_NUMBER", "type": "integer", "nullable": true, "metadata": {}}, {"name": "ENTRY_DATE", "type": "date", "nullable": true, "metadata": {}}, {"name": "TIME_STAMP", "type": "string", "nullable": true, "metadata": {}}, {"name": "VERSION", "type": "string", "nullable": true, "metadata": {}}, {"name": "FILE_TYPE", "type": "string", "nullable": true, "metadata": {}}, {"name": "filename", "type": "string", "nullable": true, "metadata": {}}, {"name": "filename", "type": "string", "nullable": true, "metadata": {}}]}